user_fields/__init__.py
user_fields/apps.py
user_fields/decorators.py
user_fields/mixins.py
user_fields/models.py
user_fields/tests.py
user_fields/utils.py
user_fields/views.py
user_fields/migrations/0001_initial.py
user_fields/migrations/0002_auto_20210911_1710.py
user_fields/migrations/__init__.py
django_user_fields-0.1.1.dist-info/LICENSE.txt
django_user_fields-0.1.1.dist-info/METADATA
django_user_fields-0.1.1.dist-info/WHEEL
django_user_fields-0.1.1.dist-info/top_level.txt
django_user_fields-0.1.1.dist-info/RECORD
