Metadata-Version: 2.1
Name: django-user-fields
Version: 0.1.1
Summary: A Django application that makes user creation of form fields simple.
Home-page: https://github.com/Rishk/django-user-fields
Author: Rishi Hindocha
Author-email: rishi@linux.com
License: MIT
Keywords: django custom user defined form fields
Platform: UNKNOWN
Classifier: Development Status :: 4 - Beta
Classifier: Environment :: Web Environment
Classifier: Framework :: Django
Classifier: License :: OSI Approved :: MIT License
Classifier: Natural Language :: English
Classifier: Operating System :: OS Independent
Classifier: Programming Language :: Python :: 3
Classifier: Programming Language :: Python :: 3.5
Classifier: Programming Language :: Python :: 3.6
Classifier: Programming Language :: Python :: 3.7
Classifier: Programming Language :: Python :: 3.8
Classifier: Programming Language :: Python :: 3.9
Classifier: Topic :: Software Development :: Libraries :: Application Frameworks
Classifier: Topic :: Software Development :: Libraries :: Python Modules
License-File: LICENSE.txt
Requires-Dist: Django (>=2.0)
